[
  {
    "id": "1",
    "thumbnailUrl": "drawable/dis_1",
    "title": "Video 1",
    "author": "Author 1",
    "authorProfilePicUrl": "drawable/pro_1",
    "views": 1000,
    "uploadTime": "1 day ago",
    "videoUrl": "raw/vid1",
    "category": "Sport",
    "likes": 0
  },
  {
    "id": "2",
    "thumbnailUrl": "drawable/dis_2",
    "title": "Video 2",
    "author": "Author 2",
    "authorProfilePicUrl": "drawable/pro_2",
    "views": 2000,
    "uploadTime": "2 days ago",
    "videoUrl": "raw/vid2",
    "category": "News",
    "likes": 20
  },
  {
    "id": "3",
    "thumbnailUrl": "drawable/dis_3",
    "title": "Video 3",
    "author": "Author 3",
    "authorProfilePicUrl": "drawable/pro_3",
    "views": 3000,
    "uploadTime": "3 days ago",
    "videoUrl": "raw/vid3",
    "category": "Cinema",
    "likes": 30
  },
  {
    "id": "4",
    "thumbnailUrl": "drawable/dis_4",
    "title": "Video 4",
    "author": "Author 4",
    "authorProfilePicUrl": "drawable/pro_4",
    "views": 4000,
    "uploadTime": "4 days ago",
    "videoUrl": "raw/vid4",
    "category": "Gaming",
    "likes": 40
  },
  {
    "id": "5",
    "thumbnailUrl": "drawable/dis_5",
    "title": "Video 5",
    "author": "Author 1",
    "authorProfilePicUrl": "drawable/pro_1",
    "views":  5000,
    "uploadTime": "5 days ago",
    "videoUrl": "raw/vid5",
    "category": "Sport",
    "likes": 50
  },
  {
    "id": "6",
    "thumbnailUrl": "drawable/dis_6",
    "title": "Video 6",
    "author": "Author 2",
    "authorProfilePicUrl": "drawable/pro_2",
    "views": 6000,
    "uploadTime": "6 days ago",
    "videoUrl": "raw/vid6",
    "category": "News",
    "likes": 60
  },
  {
    "id": "7",
    "thumbnailUrl": "drawable/dis_7",
    "title": "Video 7",
    "author": "Author 3",
    "authorProfilePicUrl": "drawable/pro_3",
    "views": 7000,
    "uploadTime": "7 days ago",
    "videoUrl": "raw/vid7",
    "category": "Cinema",
    "likes": 70
  },
  {
    "id": "8",
    "thumbnailUrl": "drawable/dis_8",
    "title": "Video 8",
    "author": "Author 3",
    "authorProfilePicUrl": "drawable/pro_3",
    "views": 8000,
    "uploadTime": "8 days ago",
    "videoUrl": "raw/vid8",
    "category": "Gaming",
    "likes": 80
  },
  {
    "id": "9",
    "thumbnailUrl": "drawable/dis_9",
    "title": "Video 9",
    "author": "Author 1",
    "authorProfilePicUrl": "drawable/pro_1",
    "views": 9000,
    "uploadTime": "9 days ago",
    "videoUrl": "raw/vid9",
    "category": "Sport",
    "likes": 90
  },
  {
    "id": "10",
    "thumbnailUrl": "drawable/dis_10",
    "title": "Video 10",
    "author": "Author 1",
    "authorProfilePicUrl": "drawable/pro_1",
    "views": 10000,
    "uploadTime": "10 days ago",
    "videoUrl": "raw/vid10",
    "category": "News",
    "likes": 100
  },
  {
    "id": "11",
    "thumbnailUrl": "drawable/dis_11",
    "title": "Video 11",
    "author": "Author 4",
    "authorProfilePicUrl": "drawable/pro_4",
    "views": 11000,
    "uploadTime": "11 days ago",
    "videoUrl": "raw/vid11",
    "category": "Cinema",
    "likes": 110
  },
  {
    "id": "12",
    "thumbnailUrl": "drawable/dis_12",
    "title": "Video 12",
    "author": "Author 4",
    "authorProfilePicUrl": "drawable/pro_4",
    "views": 12000,
    "uploadTime": "12 days ago",
    "videoUrl": "raw/vid12",
    "category": "Gaming",
    "likes": 120
  },
  {
    "id": "13",
    "thumbnailUrl": "drawable/dis_13",
    "title": "Video 13",
    "author": "Author 2",
    "authorProfilePicUrl": "drawable/pro_2",
    "views": 13000,
    "uploadTime": "13 days ago",
    "videoUrl": "raw/vid13",
    "category": "Sport",
    "likes": 130
  },
  {
    "id": "14",
    "thumbnailUrl": "drawable/dis_14",
    "title": "Video 14",
    "author": "Author 2",
    "authorProfilePicUrl": "drawable/pro_2",
    "views": 14000,
    "uploadTime": "14 days ago",
    "videoUrl": "raw/vid14",
    "category": "News",
    "likes": 140
  }
]